apc_smartconnect/APCSmartConnect.py
apc_smartconnect/__init__.py
apc_smartconnect-1.0.1.dist-info/LICENSE
apc_smartconnect-1.0.1.dist-info/METADATA
apc_smartconnect-1.0.1.dist-info/WHEEL
apc_smartconnect-1.0.1.dist-info/top_level.txt
apc_smartconnect-1.0.1.dist-info/RECORD
